{
  "source": "/mnt/data/index(1).html",
  "original_bytes": 2527240,
  "output_bytes": 2501875,
  "removed_blocks": [
    {
      "label": "CHEREPOVETS 89 FINAL SAFE PATCH",
      "count": 1
    },
    {
      "label": "CH89 LEGACY RESTORE V6",
      "count": 1
    },
    {
      "label": "CH89 LEGACY RESTORE V7",
      "count": 1
    },
    {
      "label": "CH89 LEGACY RESTORE V7 EARLY",
      "count": 1
    }
  ],
  "removed_org_button_count": 1,
  "removed_org_subnav_count": 1,
  "removed_static_fsb_sections_count": 1,
  "removed_fsb_admin_options_count": 1,
  "removed_fsb_role_options_count": 0,
  "auth_script_present": true,
  "support_button_present": true,
  "organization_top_button_present": false,
  "legacy_breaking_blocks_present": false
}